gptexec.py
gptexec-1.0.0.dist-info/LICENSE
gptexec-1.0.0.dist-info/METADATA
gptexec-1.0.0.dist-info/WHEEL
gptexec-1.0.0.dist-info/top_level.txt
gptexec-1.0.0.dist-info/RECORD
