Metadata-Version: 2.1
Name: gptexec
Version: 1.0.0
Summary: An executable Python file for executing GPT commands
Author: Tony Lampada
License-File: LICENSE
